{
  "rates": [
    {
      "currency": "USD 미국",
      "baseRate": "1,471.90",
      "change": "0.90",
      "changeDirection": "하락",
      "changeRate": "-0.06",
      "cashBuy": "1,497.65",
      "cashSell": "1,446.15",
      "send": "1,486.10",
      "receive": "1,457.70"
    },
    {
      "currency": "JPY 일본",
      "baseRate": "928.47",
      "change": "3.14",
      "changeDirection": "상승",
      "changeRate": "0.34",
      "cashBuy": "944.71",
      "cashSell": "912.23",
      "send": "937.47",
      "receive": "919.47"
    },
    {
      "currency": "EUR 유럽",
      "baseRate": "1,712.70",
      "change": "2.30",
      "changeDirection": "하락",
      "changeRate": "-0.13",
      "cashBuy": "1,746.61",
      "cashSell": "1,678.79",
      "send": "1,729.82",
      "receive": "1,695.58"
    },
    {
      "currency": "CNY 중국",
      "baseRate": "211.23",
      "change": "0.02",
      "changeDirection": "하락",
      "changeRate": "-0.01",
      "cashBuy": "223.90",
      "cashSell": "200.67",
      "send": "213.34",
      "receive": "209.12"
    },
    {
      "currency": "HKD 홍콩",
      "baseRate": "188.76",
      "change": "0.05",
      "changeDirection": "하락",
      "changeRate": "-0.03",
      "cashBuy": "192.51",
      "cashSell": "185.01",
      "send": "190.64",
      "receive": "186.88"
    },
    {
      "currency": "GBP 영국",
      "baseRate": "1,976.03",
      "change": "1.20",
      "changeDirection": "하락",
      "changeRate": "-0.06",
      "cashBuy": "2,015.35",
      "cashSell": "1,936.71",
      "send": "1,995.79",
      "receive": "1,956.27"
    },
    {
      "currency": "CHF 스위스",
      "baseRate": "1,838.27",
      "change": "0.55",
      "changeDirection": "하락",
      "changeRate": "-0.03",
      "cashBuy": "1,874.85",
      "cashSell": "1,801.69",
      "send": "1,856.65",
      "receive": "1,819.89"
    },
    {
      "currency": "CAD 캐나다",
      "baseRate": "1,058.92",
      "change": "1.64",
      "changeDirection": "하락",
      "changeRate": "-0.15",
      "cashBuy": "1,079.99",
      "cashSell": "1,037.85",
      "send": "1,069.50",
      "receive": "1,048.34"
    },
    {
      "currency": "AUD 호주",
      "baseRate": "981.90",
      "change": "3.04",
      "changeDirection": "하락",
      "changeRate": "-0.31",
      "cashBuy": "1,001.43",
      "cashSell": "962.37",
      "send": "991.71",
      "receive": "972.09"
    },
    {
      "currency": "NZD 뉴질랜드",
      "baseRate": "843.84",
      "change": "1.77",
      "changeDirection": "하락",
      "changeRate": "-0.21",
      "cashBuy": "860.63",
      "cashSell": "827.05",
      "send": "852.27",
      "receive": "835.41"
    },
    {
      "currency": "SEK 스웨덴",
      "baseRate": "159.97",
      "change": "0.29",
      "changeDirection": "상승",
      "changeRate": "0.18",
      "cashBuy": "163.96",
      "cashSell": "155.98",
      "send": "161.56",
      "receive": "158.38"
    },
    {
      "currency": "DKK 덴마크",
      "baseRate": "229.21",
      "change": "0.30",
      "changeDirection": "하락",
      "changeRate": "-0.13",
      "cashBuy": "234.94",
      "cashSell": "223.48",
      "send": "231.50",
      "receive": "226.92"
    },
    {
      "currency": "NOK 노르웨이",
      "baseRate": "146.18",
      "change": "0.21",
      "changeDirection": "상승",
      "changeRate": "0.14",
      "cashBuy": "149.83",
      "cashSell": "142.53",
      "send": "147.64",
      "receive": "144.72"
    },
    {
      "currency": "SAR 사우디아라비아",
      "baseRate": "392.48",
      "change": "0.25",
      "changeDirection": "하락",
      "changeRate": "-0.06",
      "cashBuy": "412.10",
      "cashSell": "365.01",
      "send": "396.40",
      "receive": "388.56"
    },
    {
      "currency": "KWD 쿠웨이트",
      "baseRate": "4,813.28",
      "change": "2.94",
      "changeDirection": "하락",
      "changeRate": "-0.06",
      "cashBuy": "5,102.07",
      "cashSell": "4,428.22",
      "send": "4,861.41",
      "receive": "4,765.15"
    },
    {
      "currency": "BHD 바레인",
      "baseRate": "3,904.45",
      "change": "1.87",
      "changeDirection": "하락",
      "changeRate": "-0.05",
      "cashBuy": "4,138.71",
      "cashSell": "3,592.10",
      "send": "3,943.49",
      "receive": "3,865.41"
    },
    {
      "currency": "AED 아랍에미리트",
      "baseRate": "400.78",
      "change": "0.24",
      "changeDirection": "하락",
      "changeRate": "-0.06",
      "cashBuy": "420.81",
      "cashSell": "372.73",
      "send": "404.78",
      "receive": "396.78"
    },
    {
      "currency": "THB 태국",
      "baseRate": "46.74",
      "change": "0.03",
      "changeDirection": "하락",
      "changeRate": "-0.06",
      "cashBuy": "49.52",
      "cashSell": "43.47",
      "send": "47.20",
      "receive": "46.28"
    },
    {
      "currency": "SGD 싱가포르",
      "baseRate": "1,142.69",
      "change": "0.17",
      "changeDirection": "하락",
      "changeRate": "-0.01",
      "cashBuy": "1,165.54",
      "cashSell": "1,119.84",
      "send": "1,154.11",
      "receive": "1,131.27"
    },
    {
      "currency": "IDR 인도네시아",
      "baseRate": "8.73",
      "change": "0.17",
      "changeDirection": "하락",
      "changeRate": "-0.01",
      "cashBuy": "9.42",
      "cashSell": "7.77",
      "send": "8.81",
      "receive": "8.65"
    },
    {
      "currency": "INR 인도",
      "baseRate": "16.31",
      "change": "0.75",
      "changeDirection": "하락",
      "changeRate": "-0.18",
      "cashBuy": "17.77",
      "cashSell": "14.85",
      "send": "16.47",
      "receive": "16.15"
    },
    {
      "currency": "MYR 말레이시아",
      "baseRate": "363.52",
      "change": "0.54",
      "changeDirection": "상승",
      "changeRate": "0.15",
      "cashBuy": "385.33",
      "cashSell": "334.44",
      "send": "367.15",
      "receive": "359.89"
    },
    {
      "currency": "PKR 파키스탄",
      "baseRate": "5.26",
      "change": "0.54",
      "changeDirection": "상승",
      "changeRate": "0.15",
      "cashBuy": "5.68",
      "cashSell": "4.84",
      "send": "5.31",
      "receive": "5.21"
    },
    {
      "currency": "BDT 방글라데시",
      "baseRate": "12.05",
      "change": "0.54",
      "changeDirection": "상승",
      "changeRate": "0.15",
      "cashBuy": "13.01",
      "cashSell": "11.09",
      "send": "12.17",
      "receive": "11.93"
    },
    {
      "currency": "PHP 필리핀",
      "baseRate": "24.77",
      "change": "0.05",
      "changeDirection": "하락",
      "changeRate": "-0.20",
      "cashBuy": "27.24",
      "cashSell": "23.04",
      "send": "25.01",
      "receive": "24.53"
    },
    {
      "currency": "EGP 이집트",
      "baseRate": "31.12",
      "change": "0.15",
      "changeDirection": "하락",
      "changeRate": "-0.48",
      "cashBuy": "33.60",
      "cashSell": "28.95",
      "send": "31.43",
      "receive": "30.81"
    },
    {
      "currency": "MXN 멕시코",
      "baseRate": "82.69",
      "change": "0.06",
      "changeDirection": "상승",
      "changeRate": "0.07",
      "cashBuy": "89.30",
      "cashSell": "76.08",
      "send": "83.51",
      "receive": "81.87"
    },
    {
      "currency": "BND 브루나이",
      "baseRate": "1,143.31",
      "change": "0.45",
      "changeDirection": "상승",
      "changeRate": "0.04",
      "cashBuy": "1,189.04",
      "cashSell": "1,074.72",
      "send": "1,154.74",
      "receive": "1,131.88"
    }
  ],
  "date": "2026년01월15일",
  "round": "218"
}