{
  "rates": [
    {
      "currency": "USD 미국",
      "baseRate": "1,476.50",
      "change": "2.10",
      "changeDirection": "하락",
      "changeRate": "-0.14",
      "cashBuy": "1,502.33",
      "cashSell": "1,450.67",
      "send": "1,490.80",
      "receive": "1,462.20"
    },
    {
      "currency": "JPY 일본",
      "baseRate": "949.33",
      "change": "0.68",
      "changeDirection": "하락",
      "changeRate": "-0.07",
      "cashBuy": "965.94",
      "cashSell": "932.72",
      "send": "958.53",
      "receive": "940.13"
    },
    {
      "currency": "EUR 유럽",
      "baseRate": "1,731.34",
      "change": "4.83",
      "changeDirection": "하락",
      "changeRate": "-0.28",
      "cashBuy": "1,765.62",
      "cashSell": "1,697.06",
      "send": "1,748.65",
      "receive": "1,714.03"
    },
    {
      "currency": "CNY 중국",
      "baseRate": "209.94",
      "change": "0.30",
      "changeDirection": "하락",
      "changeRate": "-0.14",
      "cashBuy": "222.53",
      "cashSell": "199.45",
      "send": "212.03",
      "receive": "207.85"
    },
    {
      "currency": "HKD 홍콩",
      "baseRate": "189.76",
      "change": "0.29",
      "changeDirection": "하락",
      "changeRate": "-0.15",
      "cashBuy": "193.53",
      "cashSell": "185.99",
      "send": "191.65",
      "receive": "187.87"
    },
    {
      "currency": "GBP 영국",
      "baseRate": "1,975.85",
      "change": "1.85",
      "changeDirection": "하락",
      "changeRate": "-0.09",
      "cashBuy": "2,015.16",
      "cashSell": "1,936.54",
      "send": "1,995.60",
      "receive": "1,956.10"
    },
    {
      "currency": "CHF 스위스",
      "baseRate": "1,859.34",
      "change": "0.28",
      "changeDirection": "상승",
      "changeRate": "0.02",
      "cashBuy": "1,896.34",
      "cashSell": "1,822.34",
      "send": "1,877.93",
      "receive": "1,840.75"
    },
    {
      "currency": "CAD 캐나다",
      "baseRate": "1,071.87",
      "change": "0.67",
      "changeDirection": "하락",
      "changeRate": "-0.06",
      "cashBuy": "1,093.20",
      "cashSell": "1,050.54",
      "send": "1,082.58",
      "receive": "1,061.16"
    },
    {
      "currency": "AUD 호주",
      "baseRate": "976.41",
      "change": "0.28",
      "changeDirection": "하락",
      "changeRate": "-0.03",
      "cashBuy": "995.84",
      "cashSell": "956.98",
      "send": "986.17",
      "receive": "966.65"
    },
    {
      "currency": "NZD 뉴질랜드",
      "baseRate": "852.68",
      "change": "0.84",
      "changeDirection": "하락",
      "changeRate": "-0.10",
      "cashBuy": "869.64",
      "cashSell": "835.72",
      "send": "861.20",
      "receive": "844.16"
    },
    {
      "currency": "SEK 스웨덴",
      "baseRate": "159.10",
      "change": "0.18",
      "changeDirection": "상승",
      "changeRate": "0.11",
      "cashBuy": "163.07",
      "cashSell": "155.13",
      "send": "160.69",
      "receive": "157.51"
    },
    {
      "currency": "DKK 덴마크",
      "baseRate": "231.72",
      "change": "0.66",
      "changeDirection": "하락",
      "changeRate": "-0.28",
      "cashBuy": "237.51",
      "cashSell": "225.93",
      "send": "234.03",
      "receive": "229.41"
    },
    {
      "currency": "NOK 노르웨이",
      "baseRate": "145.35",
      "change": "0.45",
      "changeDirection": "상승",
      "changeRate": "0.31",
      "cashBuy": "148.98",
      "cashSell": "141.72",
      "send": "146.80",
      "receive": "143.90"
    },
    {
      "currency": "SAR 사우디아라비아",
      "baseRate": "393.64",
      "change": "0.56",
      "changeDirection": "하락",
      "changeRate": "-0.14",
      "cashBuy": "413.32",
      "cashSell": "366.09",
      "send": "397.57",
      "receive": "389.71"
    },
    {
      "currency": "KWD 쿠웨이트",
      "baseRate": "4,809.13",
      "change": "8.41",
      "changeDirection": "하락",
      "changeRate": "-0.17",
      "cashBuy": "5,097.67",
      "cashSell": "4,424.40",
      "send": "4,857.22",
      "receive": "4,761.04"
    },
    {
      "currency": "BHD 바레인",
      "baseRate": "3,916.13",
      "change": "5.68",
      "changeDirection": "하락",
      "changeRate": "-0.14",
      "cashBuy": "4,151.09",
      "cashSell": "3,602.84",
      "send": "3,955.29",
      "receive": "3,876.97"
    },
    {
      "currency": "AED 아랍에미리트",
      "baseRate": "402.00",
      "change": "0.60",
      "changeDirection": "하락",
      "changeRate": "-0.15",
      "cashBuy": "422.10",
      "cashSell": "373.86",
      "send": "406.02",
      "receive": "397.98"
    },
    {
      "currency": "THB 태국",
      "baseRate": "47.02",
      "change": "0.05",
      "changeDirection": "상승",
      "changeRate": "0.11",
      "cashBuy": "49.82",
      "cashSell": "43.73",
      "send": "47.49",
      "receive": "46.55"
    },
    {
      "currency": "SGD 싱가포르",
      "baseRate": "1,144.66",
      "change": "0.57",
      "changeDirection": "하락",
      "changeRate": "-0.05",
      "cashBuy": "1,167.55",
      "cashSell": "1,121.77",
      "send": "1,156.10",
      "receive": "1,133.22"
    },
    {
      "currency": "IDR 인도네시아",
      "baseRate": "8.83",
      "change": "0.03",
      "changeDirection": "하락",
      "changeRate": "-0.34",
      "cashBuy": "9.53",
      "cashSell": "7.86",
      "send": "8.91",
      "receive": "8.75"
    },
    {
      "currency": "INR 인도",
      "baseRate": "16.36",
      "change": "0.01",
      "changeDirection": "상승",
      "changeRate": "0.06",
      "cashBuy": "17.83",
      "cashSell": "14.89",
      "send": "16.52",
      "receive": "16.20"
    },
    {
      "currency": "MYR 말레이시아",
      "baseRate": "361.53",
      "change": "0.12",
      "changeDirection": "하락",
      "changeRate": "-0.03",
      "cashBuy": "383.22",
      "cashSell": "332.61",
      "send": "365.14",
      "receive": "357.92"
    },
    {
      "currency": "PKR 파키스탄",
      "baseRate": "5.27",
      "change": "0.01",
      "changeDirection": "하락",
      "changeRate": "-0.19",
      "cashBuy": "5.69",
      "cashSell": "4.85",
      "send": "5.32",
      "receive": "5.22"
    },
    {
      "currency": "BDT 방글라데시",
      "baseRate": "12.07",
      "change": "0.03",
      "changeDirection": "하락",
      "changeRate": "-0.25",
      "cashBuy": "13.03",
      "cashSell": "11.11",
      "send": "12.19",
      "receive": "11.95"
    },
    {
      "currency": "PHP 필리핀",
      "baseRate": "25.20",
      "change": "0.01",
      "changeDirection": "상승",
      "changeRate": "0.04",
      "cashBuy": "27.72",
      "cashSell": "23.44",
      "send": "25.45",
      "receive": "24.95"
    },
    {
      "currency": "EGP 이집트",
      "baseRate": "31.06",
      "change": "0.01",
      "changeDirection": "상승",
      "changeRate": "0.04",
      "cashBuy": "33.54",
      "cashSell": "28.89",
      "send": "31.37",
      "receive": "30.75"
    },
    {
      "currency": "MXN 멕시코",
      "baseRate": "82.07",
      "change": "0.01",
      "changeDirection": "하락",
      "changeRate": "-0.01",
      "cashBuy": "88.63",
      "cashSell": "75.51",
      "send": "82.89",
      "receive": "81.25"
    },
    {
      "currency": "BND 브루나이",
      "baseRate": "1,144.71",
      "change": "0.52",
      "changeDirection": "하락",
      "changeRate": "-0.05",
      "cashBuy": "1,190.49",
      "cashSell": "1,076.03",
      "send": "1,156.15",
      "receive": "1,133.27"
    }
  ],
  "date": "2025년12월19일",
  "round": "2"
}