{
  "rates": [
    {
      "currency": "USD 미국",
      "baseRate": "1,459.50",
      "change": "6.90",
      "changeDirection": "하락",
      "changeRate": "-0.47",
      "cashBuy": "1,485.04",
      "cashSell": "1,433.96",
      "send": "1,473.60",
      "receive": "1,445.40"
    },
    {
      "currency": "JPY 일본",
      "baseRate": "944.29",
      "change": "3.46",
      "changeDirection": "하락",
      "changeRate": "-0.37",
      "cashBuy": "960.81",
      "cashSell": "927.77",
      "send": "953.44",
      "receive": "935.14"
    },
    {
      "currency": "EUR 유럽",
      "baseRate": "1,699.00",
      "change": "1.00",
      "changeDirection": "하락",
      "changeRate": "-0.06",
      "cashBuy": "1,732.64",
      "cashSell": "1,665.36",
      "send": "1,715.99",
      "receive": "1,682.01"
    },
    {
      "currency": "CNY 중국",
      "baseRate": "205.60",
      "change": "0.56",
      "changeDirection": "하락",
      "changeRate": "-0.27",
      "cashBuy": "217.93",
      "cashSell": "195.32",
      "send": "207.65",
      "receive": "203.55"
    },
    {
      "currency": "HKD 홍콩",
      "baseRate": "187.83",
      "change": "0.87",
      "changeDirection": "하락",
      "changeRate": "-0.46",
      "cashBuy": "191.56",
      "cashSell": "184.10",
      "send": "189.70",
      "receive": "185.96"
    },
    {
      "currency": "GBP 영국",
      "baseRate": "1,920.26",
      "change": "5.27",
      "changeDirection": "하락",
      "changeRate": "-0.27",
      "cashBuy": "1,958.47",
      "cashSell": "1,882.05",
      "send": "1,939.46",
      "receive": "1,901.06"
    },
    {
      "currency": "CHF 스위스",
      "baseRate": "1,844.43",
      "change": "5.91",
      "changeDirection": "상승",
      "changeRate": "0.32",
      "cashBuy": "1,881.13",
      "cashSell": "1,807.73",
      "send": "1,862.87",
      "receive": "1,825.99"
    },
    {
      "currency": "CAD 캐나다",
      "baseRate": "1,040.05",
      "change": "6.59",
      "changeDirection": "하락",
      "changeRate": "-0.63",
      "cashBuy": "1,060.74",
      "cashSell": "1,019.36",
      "send": "1,050.45",
      "receive": "1,029.65"
    },
    {
      "currency": "AUD 호주",
      "baseRate": "952.76",
      "change": "5.68",
      "changeDirection": "하락",
      "changeRate": "-0.59",
      "cashBuy": "971.71",
      "cashSell": "933.81",
      "send": "962.28",
      "receive": "943.24"
    },
    {
      "currency": "NZD 뉴질랜드",
      "baseRate": "828.70",
      "change": "1.65",
      "changeDirection": "하락",
      "changeRate": "-0.20",
      "cashBuy": "845.19",
      "cashSell": "812.21",
      "send": "836.98",
      "receive": "820.42"
    },
    {
      "currency": "SEK 스웨덴",
      "baseRate": "155.19",
      "change": "0.01",
      "changeDirection": "상승",
      "changeRate": "0.01",
      "cashBuy": "159.06",
      "cashSell": "151.32",
      "send": "156.74",
      "receive": "153.64"
    },
    {
      "currency": "DKK 덴마크",
      "baseRate": "227.53",
      "change": "0.13",
      "changeDirection": "하락",
      "changeRate": "-0.06",
      "cashBuy": "233.21",
      "cashSell": "221.85",
      "send": "229.80",
      "receive": "225.26"
    },
    {
      "currency": "NOK 노르웨이",
      "baseRate": "145.59",
      "change": "0.14",
      "changeDirection": "상승",
      "changeRate": "0.10",
      "cashBuy": "149.22",
      "cashSell": "141.96",
      "send": "147.04",
      "receive": "144.14"
    },
    {
      "currency": "SAR 사우디아라비아",
      "baseRate": "389.20",
      "change": "1.80",
      "changeDirection": "하락",
      "changeRate": "-0.46",
      "cashBuy": "408.66",
      "cashSell": "361.96",
      "send": "393.09",
      "receive": "385.31"
    },
    {
      "currency": "KWD 쿠웨이트",
      "baseRate": "4,758.88",
      "change": "15.96",
      "changeDirection": "하락",
      "changeRate": "-0.33",
      "cashBuy": "5,044.41",
      "cashSell": "4,378.17",
      "send": "4,806.46",
      "receive": "4,711.30"
    },
    {
      "currency": "BHD 바레인",
      "baseRate": "3,871.04",
      "change": "18.31",
      "changeDirection": "하락",
      "changeRate": "-0.47",
      "cashBuy": "4,103.30",
      "cashSell": "3,561.36",
      "send": "3,909.75",
      "receive": "3,832.33"
    },
    {
      "currency": "AED 아랍에미리트",
      "baseRate": "397.37",
      "change": "1.91",
      "changeDirection": "하락",
      "changeRate": "-0.48",
      "cashBuy": "417.23",
      "cashSell": "369.56",
      "send": "401.34",
      "receive": "393.40"
    },
    {
      "currency": "THB 태국",
      "baseRate": "45.11",
      "change": "0.20",
      "changeDirection": "하락",
      "changeRate": "-0.44",
      "cashBuy": "47.79",
      "cashSell": "41.96",
      "send": "45.56",
      "receive": "44.66"
    },
    {
      "currency": "SGD 싱가포르",
      "baseRate": "1,122.00",
      "change": "4.53",
      "changeDirection": "하락",
      "changeRate": "-0.40",
      "cashBuy": "1,144.44",
      "cashSell": "1,099.56",
      "send": "1,133.22",
      "receive": "1,110.78"
    },
    {
      "currency": "IDR 인도네시아",
      "baseRate": "8.74",
      "change": "0.04",
      "changeDirection": "하락",
      "changeRate": "-0.46",
      "cashBuy": "9.43",
      "cashSell": "7.78",
      "send": "8.82",
      "receive": "8.66"
    },
    {
      "currency": "INR 인도",
      "baseRate": "16.43",
      "change": "0.12",
      "changeDirection": "하락",
      "changeRate": "-0.73",
      "cashBuy": "17.90",
      "cashSell": "14.96",
      "send": "16.59",
      "receive": "16.27"
    },
    {
      "currency": "MYR 말레이시아",
      "baseRate": "353.18",
      "change": "1.32",
      "changeDirection": "하락",
      "changeRate": "-0.37",
      "cashBuy": "374.37",
      "cashSell": "324.93",
      "send": "356.71",
      "receive": "349.65"
    },
    {
      "currency": "PKR 파키스탄",
      "baseRate": "5.16",
      "change": "0.03",
      "changeDirection": "하락",
      "changeRate": "-0.58",
      "cashBuy": "5.57",
      "cashSell": "4.75",
      "send": "5.21",
      "receive": "5.11"
    },
    {
      "currency": "BDT 방글라데시",
      "baseRate": "11.94",
      "change": "0.07",
      "changeDirection": "하락",
      "changeRate": "-0.58",
      "cashBuy": "12.89",
      "cashSell": "10.99",
      "send": "12.05",
      "receive": "11.83"
    },
    {
      "currency": "PHP 필리핀",
      "baseRate": "24.74",
      "change": "0.06",
      "changeDirection": "하락",
      "changeRate": "-0.24",
      "cashBuy": "27.21",
      "cashSell": "23.01",
      "send": "24.98",
      "receive": "24.50"
    },
    {
      "currency": "EGP 이집트",
      "baseRate": "30.93",
      "change": "0.14",
      "changeDirection": "하락",
      "changeRate": "-0.45",
      "cashBuy": "33.40",
      "cashSell": "28.77",
      "send": "31.23",
      "receive": "30.63"
    },
    {
      "currency": "MXN 멕시코",
      "baseRate": "79.69",
      "change": "0.42",
      "changeDirection": "하락",
      "changeRate": "-0.52",
      "cashBuy": "86.06",
      "cashSell": "73.32",
      "send": "80.48",
      "receive": "78.90"
    },
    {
      "currency": "BND 브루나이",
      "baseRate": "1,122.00",
      "change": "4.53",
      "changeDirection": "하락",
      "changeRate": "-0.40",
      "cashBuy": "1,166.88",
      "cashSell": "1,054.68",
      "send": "1,133.22",
      "receive": "1,110.78"
    }
  ],
  "date": "2025년11월14일",
  "round": "931"
}