{
  "rates": [
    {
      "currency": "USD 미국",
      "baseRate": "1,456.80",
      "change": "9.80",
      "changeDirection": "상승",
      "changeRate": "0.68",
      "cashBuy": "1,482.29",
      "cashSell": "1,431.31",
      "send": "1,470.90",
      "receive": "1,442.70"
    },
    {
      "currency": "JPY 일본",
      "baseRate": "950.54",
      "change": "11.11",
      "changeDirection": "상승",
      "changeRate": "1.18",
      "cashBuy": "967.17",
      "cashSell": "933.91",
      "send": "959.76",
      "receive": "941.32"
    },
    {
      "currency": "EUR 유럽",
      "baseRate": "1,680.56",
      "change": "17.31",
      "changeDirection": "상승",
      "changeRate": "1.04",
      "cashBuy": "1,713.83",
      "cashSell": "1,647.29",
      "send": "1,697.36",
      "receive": "1,663.76"
    },
    {
      "currency": "CNY 중국",
      "baseRate": "204.42",
      "change": "1.51",
      "changeDirection": "상승",
      "changeRate": "0.74",
      "cashBuy": "216.68",
      "cashSell": "194.20",
      "send": "206.46",
      "receive": "202.38"
    },
    {
      "currency": "HKD 홍콩",
      "baseRate": "187.38",
      "change": "1.26",
      "changeDirection": "상승",
      "changeRate": "0.68",
      "cashBuy": "191.10",
      "cashSell": "183.66",
      "send": "189.25",
      "receive": "185.51"
    },
    {
      "currency": "GBP 영국",
      "baseRate": "1,911.47",
      "change": "23.21",
      "changeDirection": "상승",
      "changeRate": "1.23",
      "cashBuy": "1,949.50",
      "cashSell": "1,873.44",
      "send": "1,930.58",
      "receive": "1,892.36"
    },
    {
      "currency": "CHF 스위스",
      "baseRate": "1,803.86",
      "change": "18.21",
      "changeDirection": "상승",
      "changeRate": "1.02",
      "cashBuy": "1,839.75",
      "cashSell": "1,767.97",
      "send": "1,821.89",
      "receive": "1,785.83"
    },
    {
      "currency": "CAD 캐나다",
      "baseRate": "1,031.44",
      "change": "5.78",
      "changeDirection": "상승",
      "changeRate": "0.56",
      "cashBuy": "1,051.96",
      "cashSell": "1,010.92",
      "send": "1,041.75",
      "receive": "1,021.13"
    },
    {
      "currency": "AUD 호주",
      "baseRate": "943.86",
      "change": "2.37",
      "changeDirection": "상승",
      "changeRate": "0.25",
      "cashBuy": "962.64",
      "cashSell": "925.08",
      "send": "953.29",
      "receive": "934.43"
    },
    {
      "currency": "NZD 뉴질랜드",
      "baseRate": "818.87",
      "change": "0.57",
      "changeDirection": "하락",
      "changeRate": "-0.07",
      "cashBuy": "835.16",
      "cashSell": "802.58",
      "send": "827.05",
      "receive": "810.69"
    },
    {
      "currency": "SEK 스웨덴",
      "baseRate": "152.11",
      "change": "0.71",
      "changeDirection": "상승",
      "changeRate": "0.47",
      "cashBuy": "155.91",
      "cashSell": "148.31",
      "send": "153.63",
      "receive": "150.59"
    },
    {
      "currency": "DKK 덴마크",
      "baseRate": "225.08",
      "change": "2.28",
      "changeDirection": "상승",
      "changeRate": "1.02",
      "cashBuy": "230.70",
      "cashSell": "219.46",
      "send": "227.33",
      "receive": "222.83"
    },
    {
      "currency": "NOK 노르웨이",
      "baseRate": "142.80",
      "change": "1.13",
      "changeDirection": "상승",
      "changeRate": "0.80",
      "cashBuy": "146.37",
      "cashSell": "139.23",
      "send": "144.22",
      "receive": "141.38"
    },
    {
      "currency": "SAR 사우디아라비아",
      "baseRate": "388.44",
      "change": "2.62",
      "changeDirection": "상승",
      "changeRate": "0.68",
      "cashBuy": "407.86",
      "cashSell": "361.25",
      "send": "392.32",
      "receive": "384.56"
    },
    {
      "currency": "KWD 쿠웨이트",
      "baseRate": "4,746.05",
      "change": "35.92",
      "changeDirection": "상승",
      "changeRate": "0.76",
      "cashBuy": "5,030.81",
      "cashSell": "4,366.37",
      "send": "4,793.51",
      "receive": "4,698.59"
    },
    {
      "currency": "BHD 바레인",
      "baseRate": "3,864.19",
      "change": "25.99",
      "changeDirection": "상승",
      "changeRate": "0.68",
      "cashBuy": "4,096.04",
      "cashSell": "3,555.06",
      "send": "3,902.83",
      "receive": "3,825.55"
    },
    {
      "currency": "AED 아랍에미리트",
      "baseRate": "396.67",
      "change": "2.66",
      "changeDirection": "상승",
      "changeRate": "0.68",
      "cashBuy": "416.50",
      "cashSell": "368.91",
      "send": "400.63",
      "receive": "392.71"
    },
    {
      "currency": "THB 태국",
      "baseRate": "44.99",
      "change": "0.48",
      "changeDirection": "상승",
      "changeRate": "1.08",
      "cashBuy": "47.67",
      "cashSell": "41.85",
      "send": "45.43",
      "receive": "44.55"
    },
    {
      "currency": "SGD 싱가포르",
      "baseRate": "1,117.26",
      "change": "9.93",
      "changeDirection": "상승",
      "changeRate": "0.90",
      "cashBuy": "1,139.60",
      "cashSell": "1,094.92",
      "send": "1,128.43",
      "receive": "1,106.09"
    },
    {
      "currency": "IDR 인도네시아",
      "baseRate": "8.73",
      "change": "0.07",
      "changeDirection": "상승",
      "changeRate": "0.81",
      "cashBuy": "9.42",
      "cashSell": "7.77",
      "send": "8.81",
      "receive": "8.65"
    },
    {
      "currency": "INR 인도",
      "baseRate": "16.43",
      "change": "0.09",
      "changeDirection": "상승",
      "changeRate": "0.55",
      "cashBuy": "17.90",
      "cashSell": "14.96",
      "send": "16.59",
      "receive": "16.27"
    },
    {
      "currency": "MYR 말레이시아",
      "baseRate": "348.73",
      "change": "3.51",
      "changeDirection": "상승",
      "changeRate": "1.02",
      "cashBuy": "369.65",
      "cashSell": "320.84",
      "send": "352.21",
      "receive": "345.25"
    },
    {
      "currency": "PKR 파키스탄",
      "baseRate": "5.15",
      "change": "0.03",
      "changeDirection": "상승",
      "changeRate": "0.59",
      "cashBuy": "5.56",
      "cashSell": "4.74",
      "send": "5.20",
      "receive": "5.10"
    },
    {
      "currency": "BDT 방글라데시",
      "baseRate": "11.94",
      "change": "0.07",
      "changeDirection": "상승",
      "changeRate": "0.59",
      "cashBuy": "12.89",
      "cashSell": "10.99",
      "send": "12.05",
      "receive": "11.83"
    },
    {
      "currency": "PHP 필리핀",
      "baseRate": "24.64",
      "change": "0.01",
      "changeDirection": "상승",
      "changeRate": "0.04",
      "cashBuy": "27.10",
      "cashSell": "22.92",
      "send": "24.88",
      "receive": "24.40"
    },
    {
      "currency": "EGP 이집트",
      "baseRate": "30.80",
      "change": "0.28",
      "changeDirection": "상승",
      "changeRate": "0.92",
      "cashBuy": "33.26",
      "cashSell": "28.65",
      "send": "31.10",
      "receive": "30.50"
    },
    {
      "currency": "MXN 멕시코",
      "baseRate": "78.39",
      "change": "0.58",
      "changeDirection": "상승",
      "changeRate": "0.75",
      "cashBuy": "84.66",
      "cashSell": "72.12",
      "send": "79.17",
      "receive": "77.61"
    },
    {
      "currency": "BND 브루나이",
      "baseRate": "1,116.88",
      "change": "9.55",
      "changeDirection": "상승",
      "changeRate": "0.86",
      "cashBuy": "1,161.55",
      "cashSell": "1,049.87",
      "send": "1,128.04",
      "receive": "1,105.72"
    }
  ],
  "date": "2025년11월07일",
  "round": "426"
}