{
  "rates": [
    {
      "currency": "USD 미국",
      "baseRate": "1,397.80",
      "change": "28.80",
      "changeDirection": "하락",
      "changeRate": "-2.02",
      "cashBuy": "1,422.26",
      "cashSell": "1,373.34",
      "send": "1,411.30",
      "receive": "1,384.30"
    },
    {
      "currency": "JPY 일본",
      "baseRate": "974.08",
      "change": "21.84",
      "changeDirection": "하락",
      "changeRate": "-2.19",
      "cashBuy": "991.12",
      "cashSell": "957.04",
      "send": "983.52",
      "receive": "964.64"
    },
    {
      "currency": "EUR 유럽",
      "baseRate": "1,583.99",
      "change": "33.28",
      "changeDirection": "하락",
      "changeRate": "-2.06",
      "cashBuy": "1,615.35",
      "cashSell": "1,552.63",
      "send": "1,599.82",
      "receive": "1,568.16"
    },
    {
      "currency": "CNY 중국",
      "baseRate": "193.26",
      "change": "3.66",
      "changeDirection": "하락",
      "changeRate": "-1.86",
      "cashBuy": "204.85",
      "cashSell": "183.60",
      "send": "195.19",
      "receive": "191.33"
    },
    {
      "currency": "HKD 홍콩",
      "baseRate": "180.02",
      "change": "4.04",
      "changeDirection": "하락",
      "changeRate": "-2.19",
      "cashBuy": "183.60",
      "cashSell": "176.44",
      "send": "181.82",
      "receive": "178.22"
    },
    {
      "currency": "GBP 영국",
      "baseRate": "1,865.08",
      "change": "38.65",
      "changeDirection": "하락",
      "changeRate": "-2.03",
      "cashBuy": "1,902.19",
      "cashSell": "1,827.97",
      "send": "1,883.73",
      "receive": "1,846.43"
    },
    {
      "currency": "CHF 스위스",
      "baseRate": "1,699.45",
      "change": "27.15",
      "changeDirection": "하락",
      "changeRate": "-1.57",
      "cashBuy": "1,733.26",
      "cashSell": "1,665.64",
      "send": "1,716.44",
      "receive": "1,682.46"
    },
    {
      "currency": "CAD 캐나다",
      "baseRate": "1,011.58",
      "change": "24.14",
      "changeDirection": "하락",
      "changeRate": "-2.33",
      "cashBuy": "1,031.71",
      "cashSell": "991.45",
      "send": "1,021.69",
      "receive": "1,001.47"
    },
    {
      "currency": "AUD 호주",
      "baseRate": "902.56",
      "change": "25.37",
      "changeDirection": "하락",
      "changeRate": "-2.73",
      "cashBuy": "920.52",
      "cashSell": "884.60",
      "send": "911.58",
      "receive": "893.54"
    },
    {
      "currency": "NZD 뉴질랜드",
      "baseRate": "833.37",
      "change": "24.37",
      "changeDirection": "하락",
      "changeRate": "-2.84",
      "cashBuy": "849.95",
      "cashSell": "816.79",
      "send": "841.70",
      "receive": "825.04"
    },
    {
      "currency": "SEK 스웨덴",
      "baseRate": "145.10",
      "change": "3.89",
      "changeDirection": "하락",
      "changeRate": "-2.61",
      "cashBuy": "148.72",
      "cashSell": "141.48",
      "send": "146.55",
      "receive": "143.65"
    },
    {
      "currency": "DKK 덴마크",
      "baseRate": "212.31",
      "change": "4.44",
      "changeDirection": "하락",
      "changeRate": "-2.05",
      "cashBuy": "217.61",
      "cashSell": "207.01",
      "send": "214.43",
      "receive": "210.19"
    },
    {
      "currency": "NOK 노르웨이",
      "baseRate": "135.31",
      "change": "3.68",
      "changeDirection": "하락",
      "changeRate": "-2.65",
      "cashBuy": "138.69",
      "cashSell": "131.93",
      "send": "136.66",
      "receive": "133.96"
    },
    {
      "currency": "SAR 사우디아라비아",
      "baseRate": "372.66",
      "change": "7.68",
      "changeDirection": "하락",
      "changeRate": "-2.02",
      "cashBuy": "391.29",
      "cashSell": "346.58",
      "send": "376.38",
      "receive": "368.94"
    },
    {
      "currency": "KWD 쿠웨이트",
      "baseRate": "4,556.21",
      "change": "96.30",
      "changeDirection": "하락",
      "changeRate": "-2.07",
      "cashBuy": "4,829.58",
      "cashSell": "4,191.72",
      "send": "4,601.77",
      "receive": "4,510.65"
    },
    {
      "currency": "BHD 바레인",
      "baseRate": "3,707.30",
      "change": "76.48",
      "changeDirection": "하락",
      "changeRate": "-2.02",
      "cashBuy": "3,929.73",
      "cashSell": "3,410.72",
      "send": "3,744.37",
      "receive": "3,670.23"
    },
    {
      "currency": "AED 아랍에미리트",
      "baseRate": "380.55",
      "change": "7.85",
      "changeDirection": "하락",
      "changeRate": "-2.02",
      "cashBuy": "399.57",
      "cashSell": "353.92",
      "send": "384.35",
      "receive": "376.75"
    },
    {
      "currency": "THB 태국",
      "baseRate": "42.65",
      "change": "0.97",
      "changeDirection": "하락",
      "changeRate": "-2.22",
      "cashBuy": "45.19",
      "cashSell": "39.67",
      "send": "43.07",
      "receive": "42.23"
    },
    {
      "currency": "SGD 싱가포르",
      "baseRate": "1,080.72",
      "change": "26.07",
      "changeDirection": "하락",
      "changeRate": "-2.36",
      "cashBuy": "1,102.33",
      "cashSell": "1,059.11",
      "send": "1,091.52",
      "receive": "1,069.92"
    },
    {
      "currency": "IDR 인도네시아",
      "baseRate": "8.46",
      "change": "0.21",
      "changeDirection": "하락",
      "changeRate": "-2.42",
      "cashBuy": "9.13",
      "cashSell": "7.53",
      "send": "8.54",
      "receive": "8.38"
    },
    {
      "currency": "INR 인도",
      "baseRate": "16.50",
      "change": "0.42",
      "changeDirection": "하락",
      "changeRate": "-2.48",
      "cashBuy": "17.98",
      "cashSell": "15.02",
      "send": "16.66",
      "receive": "16.34"
    },
    {
      "currency": "MYR 말레이시아",
      "baseRate": "327.62",
      "change": "9.44",
      "changeDirection": "하락",
      "changeRate": "-2.80",
      "cashBuy": "347.27",
      "cashSell": "301.42",
      "send": "330.89",
      "receive": "324.35"
    },
    {
      "currency": "PKR 파키스탄",
      "baseRate": "4.97",
      "change": "0.10",
      "changeDirection": "하락",
      "changeRate": "-1.97",
      "cashBuy": "5.36",
      "cashSell": "4.58",
      "send": "5.01",
      "receive": "4.93"
    },
    {
      "currency": "BDT 방글라데시",
      "baseRate": "11.50",
      "change": "0.24",
      "changeDirection": "하락",
      "changeRate": "-2.04",
      "cashBuy": "12.42",
      "cashSell": "10.58",
      "send": "11.61",
      "receive": "11.39"
    },
    {
      "currency": "PHP 필리핀",
      "baseRate": "25.16",
      "change": "0.58",
      "changeDirection": "하락",
      "changeRate": "-2.25",
      "cashBuy": "27.67",
      "cashSell": "23.40",
      "send": "25.41",
      "receive": "24.91"
    },
    {
      "currency": "EGP 이집트",
      "baseRate": "27.60",
      "change": "0.56",
      "changeDirection": "하락",
      "changeRate": "-1.99",
      "cashBuy": "29.80",
      "cashSell": "25.67",
      "send": "27.87",
      "receive": "27.33"
    },
    {
      "currency": "MXN 멕시코",
      "baseRate": "71.29",
      "change": "1.32",
      "changeDirection": "하락",
      "changeRate": "-1.82",
      "cashBuy": "76.99",
      "cashSell": "65.59",
      "send": "72.00",
      "receive": "70.58"
    },
    {
      "currency": "BND 브루나이",
      "baseRate": "1,079.88",
      "change": "26.91",
      "changeDirection": "하락",
      "changeRate": "-2.43",
      "cashBuy": "1,123.07",
      "cashSell": "1,015.09",
      "send": "1,090.67",
      "receive": "1,069.09"
    }
  ],
  "date": "2025년05월08일",
  "round": "155"
}