{
  "rates": [
    {
      "currency": "USD 미국",
      "baseRate": "1,434.80",
      "change": "33.00",
      "changeDirection": "하락",
      "changeRate": "-2.25",
      "cashBuy": "1,459.90",
      "cashSell": "1,409.70",
      "send": "1,448.70",
      "receive": "1,420.90"
    },
    {
      "currency": "JPY 일본",
      "baseRate": "984.09",
      "change": "5.86",
      "changeDirection": "하락",
      "changeRate": "-0.59",
      "cashBuy": "1,001.31",
      "cashSell": "966.87",
      "send": "993.63",
      "receive": "974.55"
    },
    {
      "currency": "EUR 유럽",
      "baseRate": "1,590.91",
      "change": "1.14",
      "changeDirection": "하락",
      "changeRate": "-0.07",
      "cashBuy": "1,622.41",
      "cashSell": "1,559.41",
      "send": "1,606.81",
      "receive": "1,575.01"
    },
    {
      "currency": "CNY 중국",
      "baseRate": "198.01",
      "change": "3.42",
      "changeDirection": "하락",
      "changeRate": "-1.70",
      "cashBuy": "209.89",
      "cashSell": "188.11",
      "send": "199.99",
      "receive": "196.03"
    },
    {
      "currency": "HKD 홍콩",
      "baseRate": "184.49",
      "change": "4.08",
      "changeDirection": "하락",
      "changeRate": "-2.16",
      "cashBuy": "188.16",
      "cashSell": "180.82",
      "send": "186.33",
      "receive": "182.65"
    },
    {
      "currency": "GBP 영국",
      "baseRate": "1,879.16",
      "change": "32.58",
      "changeDirection": "하락",
      "changeRate": "-1.70",
      "cashBuy": "1,916.55",
      "cashSell": "1,841.77",
      "send": "1,897.95",
      "receive": "1,860.37"
    },
    {
      "currency": "CHF 스위스",
      "baseRate": "1,679.90",
      "change": "10.33",
      "changeDirection": "상승",
      "changeRate": "0.62",
      "cashBuy": "1,713.33",
      "cashSell": "1,646.47",
      "send": "1,696.69",
      "receive": "1,663.11"
    },
    {
      "currency": "CAD 캐나다",
      "baseRate": "1,017.73",
      "change": "11.58",
      "changeDirection": "하락",
      "changeRate": "-1.13",
      "cashBuy": "1,037.98",
      "cashSell": "997.48",
      "send": "1,027.90",
      "receive": "1,007.56"
    },
    {
      "currency": "AUD 호주",
      "baseRate": "897.04",
      "change": "20.26",
      "changeDirection": "하락",
      "changeRate": "-2.21",
      "cashBuy": "914.89",
      "cashSell": "879.19",
      "send": "906.01",
      "receive": "888.07"
    },
    {
      "currency": "NZD 뉴질랜드",
      "baseRate": "822.00",
      "change": "15.23",
      "changeDirection": "하락",
      "changeRate": "-1.82",
      "cashBuy": "838.35",
      "cashSell": "805.65",
      "send": "830.22",
      "receive": "813.78"
    },
    {
      "currency": "SEK 스웨덴",
      "baseRate": "146.95",
      "change": "1.35",
      "changeDirection": "하락",
      "changeRate": "-0.91",
      "cashBuy": "150.62",
      "cashSell": "143.28",
      "send": "148.41",
      "receive": "145.49"
    },
    {
      "currency": "DKK 덴마크",
      "baseRate": "213.21",
      "change": "0.16",
      "changeDirection": "하락",
      "changeRate": "-0.07",
      "cashBuy": "218.54",
      "cashSell": "207.88",
      "send": "215.34",
      "receive": "211.08"
    },
    {
      "currency": "NOK 노르웨이",
      "baseRate": "138.82",
      "change": "1.75",
      "changeDirection": "하락",
      "changeRate": "-1.24",
      "cashBuy": "142.29",
      "cashSell": "135.35",
      "send": "140.20",
      "receive": "137.44"
    },
    {
      "currency": "SAR 사우디아라비아",
      "baseRate": "382.45",
      "change": "8.80",
      "changeDirection": "하락",
      "changeRate": "-2.25",
      "cashBuy": "401.57",
      "cashSell": "355.68",
      "send": "386.27",
      "receive": "378.63"
    },
    {
      "currency": "KWD 쿠웨이트",
      "baseRate": "4,665.11",
      "change": "97.23",
      "changeDirection": "하락",
      "changeRate": "-2.04",
      "cashBuy": "4,945.01",
      "cashSell": "4,291.91",
      "send": "4,711.76",
      "receive": "4,618.46"
    },
    {
      "currency": "BHD 바레인",
      "baseRate": "3,806.14",
      "change": "87.44",
      "changeDirection": "하락",
      "changeRate": "-2.25",
      "cashBuy": "4,034.50",
      "cashSell": "3,501.65",
      "send": "3,844.20",
      "receive": "3,768.08"
    },
    {
      "currency": "AED 아랍에미리트",
      "baseRate": "390.63",
      "change": "8.98",
      "changeDirection": "하락",
      "changeRate": "-2.25",
      "cashBuy": "410.16",
      "cashSell": "363.29",
      "send": "394.53",
      "receive": "386.73"
    },
    {
      "currency": "THB 태국",
      "baseRate": "42.07",
      "change": "0.59",
      "changeDirection": "하락",
      "changeRate": "-1.38",
      "cashBuy": "44.57",
      "cashSell": "39.13",
      "send": "42.49",
      "receive": "41.65"
    },
    {
      "currency": "SGD 싱가포르",
      "baseRate": "1,076.77",
      "change": "11.17",
      "changeDirection": "하락",
      "changeRate": "-1.03",
      "cashBuy": "1,098.30",
      "cashSell": "1,055.24",
      "send": "1,087.53",
      "receive": "1,066.01"
    },
    {
      "currency": "IDR 인도네시아",
      "baseRate": "8.67",
      "change": "0.19",
      "changeDirection": "하락",
      "changeRate": "-2.14",
      "cashBuy": "9.36",
      "cashSell": "7.72",
      "send": "8.75",
      "receive": "8.59"
    },
    {
      "currency": "INR 인도",
      "baseRate": "16.83",
      "change": "0.34",
      "changeDirection": "하락",
      "changeRate": "-1.98",
      "cashBuy": "18.34",
      "cashSell": "15.32",
      "send": "16.99",
      "receive": "16.67"
    },
    {
      "currency": "MYR 말레이시아",
      "baseRate": "324.51",
      "change": "5.04",
      "changeDirection": "하락",
      "changeRate": "-1.53",
      "cashBuy": "343.98",
      "cashSell": "298.55",
      "send": "327.75",
      "receive": "321.27"
    },
    {
      "currency": "PKR 파키스탄",
      "baseRate": "5.11",
      "change": "0.13",
      "changeDirection": "하락",
      "changeRate": "-2.48",
      "cashBuy": "5.51",
      "cashSell": "4.71",
      "send": "5.16",
      "receive": "5.06"
    },
    {
      "currency": "BDT 방글라데시",
      "baseRate": "11.81",
      "change": "0.27",
      "changeDirection": "하락",
      "changeRate": "-2.24",
      "cashBuy": "12.75",
      "cashSell": "10.87",
      "send": "11.92",
      "receive": "11.70"
    },
    {
      "currency": "PHP 필리핀",
      "baseRate": "25.25",
      "change": "0.39",
      "changeDirection": "하락",
      "changeRate": "-1.52",
      "cashBuy": "27.77",
      "cashSell": "23.49",
      "send": "25.50",
      "receive": "25.00"
    },
    {
      "currency": "EGP 이집트",
      "baseRate": "28.36",
      "change": "0.67",
      "changeDirection": "하락",
      "changeRate": "-2.31",
      "cashBuy": "30.62",
      "cashSell": "26.38",
      "send": "28.64",
      "receive": "28.08"
    },
    {
      "currency": "MXN 멕시코",
      "baseRate": "71.91",
      "change": "0.40",
      "changeDirection": "하락",
      "changeRate": "-0.55",
      "cashBuy": "77.66",
      "cashSell": "66.16",
      "send": "72.62",
      "receive": "71.20"
    },
    {
      "currency": "BND 브루나이",
      "baseRate": "1,074.72",
      "change": "13.22",
      "changeDirection": "하락",
      "changeRate": "-1.22",
      "cashBuy": "1,117.70",
      "cashSell": "1,010.24",
      "send": "1,085.46",
      "receive": "1,063.98"
    }
  ],
  "date": "2025년04월04일",
  "round": "470"
}