{
  "rates": [
    {
      "currency": "USD 미국",
      "baseRate": "1,425.20",
      "change": "3.70",
      "changeDirection": "상승",
      "changeRate": "0.26",
      "cashBuy": "1,450.14",
      "cashSell": "1,400.26",
      "send": "1,439.00",
      "receive": "1,411.40"
    },
    {
      "currency": "JPY 일본",
      "baseRate": "1,013.37",
      "change": "9.84",
      "changeDirection": "상승",
      "changeRate": "0.98",
      "cashBuy": "1,031.10",
      "cashSell": "995.64",
      "send": "1,023.19",
      "receive": "1,003.55"
    },
    {
      "currency": "EUR 유럽",
      "baseRate": "1,639.98",
      "change": "13.86",
      "changeDirection": "상승",
      "changeRate": "0.85",
      "cashBuy": "1,672.45",
      "cashSell": "1,607.51",
      "send": "1,656.37",
      "receive": "1,623.59"
    },
    {
      "currency": "CNY 중국",
      "baseRate": "194.83",
      "change": "0.06",
      "changeDirection": "상승",
      "changeRate": "0.03",
      "cashBuy": "206.51",
      "cashSell": "185.09",
      "send": "196.77",
      "receive": "192.89"
    },
    {
      "currency": "HKD 홍콩",
      "baseRate": "183.66",
      "change": "0.51",
      "changeDirection": "상승",
      "changeRate": "0.28",
      "cashBuy": "187.31",
      "cashSell": "180.01",
      "send": "185.49",
      "receive": "181.83"
    },
    {
      "currency": "GBP 영국",
      "baseRate": "1,907.92",
      "change": "16.69",
      "changeDirection": "상승",
      "changeRate": "0.88",
      "cashBuy": "1,945.88",
      "cashSell": "1,869.96",
      "send": "1,926.99",
      "receive": "1,888.85"
    },
    {
      "currency": "CHF 스위스",
      "baseRate": "1,758.85",
      "change": "11.03",
      "changeDirection": "상승",
      "changeRate": "0.63",
      "cashBuy": "1,793.85",
      "cashSell": "1,723.85",
      "send": "1,776.43",
      "receive": "1,741.27"
    },
    {
      "currency": "CAD 캐나다",
      "baseRate": "1,030.36",
      "change": "2.41",
      "changeDirection": "상승",
      "changeRate": "0.23",
      "cashBuy": "1,050.86",
      "cashSell": "1,009.86",
      "send": "1,040.66",
      "receive": "1,020.06"
    },
    {
      "currency": "AUD 호주",
      "baseRate": "914.98",
      "change": "7.42",
      "changeDirection": "상승",
      "changeRate": "0.82",
      "cashBuy": "933.18",
      "cashSell": "896.78",
      "send": "924.12",
      "receive": "905.84"
    },
    {
      "currency": "NZD 뉴질랜드",
      "baseRate": "855.41",
      "change": "8.98",
      "changeDirection": "상승",
      "changeRate": "1.06",
      "cashBuy": "872.43",
      "cashSell": "838.39",
      "send": "863.96",
      "receive": "846.86"
    },
    {
      "currency": "SEK 스웨덴",
      "baseRate": "149.51",
      "change": "0.96",
      "changeDirection": "상승",
      "changeRate": "0.65",
      "cashBuy": "153.24",
      "cashSell": "145.78",
      "send": "151.00",
      "receive": "148.02"
    },
    {
      "currency": "DKK 덴마크",
      "baseRate": "219.62",
      "change": "1.81",
      "changeDirection": "상승",
      "changeRate": "0.83",
      "cashBuy": "225.11",
      "cashSell": "214.13",
      "send": "221.81",
      "receive": "217.43"
    },
    {
      "currency": "NOK 노르웨이",
      "baseRate": "137.47",
      "change": "1.50",
      "changeDirection": "상승",
      "changeRate": "1.10",
      "cashBuy": "140.90",
      "cashSell": "134.04",
      "send": "138.84",
      "receive": "136.10"
    },
    {
      "currency": "SAR 사우디아라비아",
      "baseRate": "379.87",
      "change": "1.02",
      "changeDirection": "상승",
      "changeRate": "0.27",
      "cashBuy": "398.86",
      "cashSell": "353.28",
      "send": "383.66",
      "receive": "376.08"
    },
    {
      "currency": "KWD 쿠웨이트",
      "baseRate": "4,656.15",
      "change": "19.97",
      "changeDirection": "상승",
      "changeRate": "0.43",
      "cashBuy": "4,935.51",
      "cashSell": "4,283.66",
      "send": "4,702.71",
      "receive": "4,609.59"
    },
    {
      "currency": "BHD 바레인",
      "baseRate": "3,781.07",
      "change": "10.51",
      "changeDirection": "상승",
      "changeRate": "0.28",
      "cashBuy": "4,007.93",
      "cashSell": "3,478.59",
      "send": "3,818.88",
      "receive": "3,743.26"
    },
    {
      "currency": "AED 아랍에미리트",
      "baseRate": "388.03",
      "change": "0.98",
      "changeDirection": "상승",
      "changeRate": "0.25",
      "cashBuy": "407.43",
      "cashSell": "360.87",
      "send": "391.91",
      "receive": "384.15"
    },
    {
      "currency": "THB 태국",
      "baseRate": "43.04",
      "change": "0.39",
      "changeDirection": "상승",
      "changeRate": "0.91",
      "cashBuy": "45.60",
      "cashSell": "40.03",
      "send": "43.47",
      "receive": "42.61"
    },
    {
      "currency": "SGD 싱가포르",
      "baseRate": "1,091.52",
      "change": "5.74",
      "changeDirection": "상승",
      "changeRate": "0.53",
      "cashBuy": "1,113.35",
      "cashSell": "1,069.69",
      "send": "1,102.43",
      "receive": "1,080.61"
    },
    {
      "currency": "IDR 인도네시아",
      "baseRate": "8.45",
      "change": "5.74",
      "changeDirection": "상승",
      "changeRate": "0.53",
      "cashBuy": "9.12",
      "cashSell": "7.53",
      "send": "8.53",
      "receive": "8.37"
    },
    {
      "currency": "INR 인도",
      "baseRate": "16.74",
      "change": "0.11",
      "changeDirection": "상승",
      "changeRate": "0.66",
      "cashBuy": "18.24",
      "cashSell": "15.24",
      "send": "16.90",
      "receive": "16.58"
    },
    {
      "currency": "MYR 말레이시아",
      "baseRate": "325.35",
      "change": "3.27",
      "changeDirection": "상승",
      "changeRate": "1.02",
      "cashBuy": "344.87",
      "cashSell": "299.33",
      "send": "328.60",
      "receive": "322.10"
    },
    {
      "currency": "PKR 파키스탄",
      "baseRate": "5.08",
      "change": "0.01",
      "changeDirection": "상승",
      "changeRate": "0.20",
      "cashBuy": "5.48",
      "cashSell": "4.68",
      "send": "5.13",
      "receive": "5.03"
    },
    {
      "currency": "BDT 방글라데시",
      "baseRate": "11.73",
      "change": "0.03",
      "changeDirection": "상승",
      "changeRate": "0.26",
      "cashBuy": "12.66",
      "cashSell": "10.80",
      "send": "11.84",
      "receive": "11.62"
    },
    {
      "currency": "PHP 필리핀",
      "baseRate": "25.12",
      "change": "0.03",
      "changeDirection": "상승",
      "changeRate": "0.12",
      "cashBuy": "27.63",
      "cashSell": "23.37",
      "send": "25.37",
      "receive": "24.87"
    },
    {
      "currency": "EGP 이집트",
      "baseRate": "27.88",
      "change": "0.07",
      "changeDirection": "상승",
      "changeRate": "0.25",
      "cashBuy": "30.11",
      "cashSell": "25.93",
      "send": "28.15",
      "receive": "27.61"
    },
    {
      "currency": "MXN 멕시코",
      "baseRate": "72.22",
      "change": "0.08",
      "changeDirection": "상승",
      "changeRate": "0.11",
      "cashBuy": "77.99",
      "cashSell": "66.45",
      "send": "72.94",
      "receive": "71.50"
    },
    {
      "currency": "BND 브루나이",
      "baseRate": "1,092.15",
      "change": "6.37",
      "changeDirection": "상승",
      "changeRate": "0.59",
      "cashBuy": "1,135.83",
      "cashSell": "1,026.63",
      "send": "1,103.07",
      "receive": "1,081.23"
    }
  ],
  "date": "2025년04월22일",
  "round": "159"
}