{
  "rates": [
    {
      "currency": "USD 미국",
      "baseRate": "1,387.50",
      "change": "10.60",
      "changeDirection": "하락",
      "changeRate": "-0.76",
      "cashBuy": "1,411.78",
      "cashSell": "1,363.22",
      "send": "1,400.90",
      "receive": "1,374.10"
    },
    {
      "currency": "JPY 일본",
      "baseRate": "941.76",
      "change": "0.39",
      "changeDirection": "하락",
      "changeRate": "-0.04",
      "cashBuy": "958.24",
      "cashSell": "925.28",
      "send": "950.89",
      "receive": "932.63"
    },
    {
      "currency": "EUR 유럽",
      "baseRate": "1,622.96",
      "change": "0.44",
      "changeDirection": "하락",
      "changeRate": "-0.03",
      "cashBuy": "1,655.09",
      "cashSell": "1,590.83",
      "send": "1,639.18",
      "receive": "1,606.74"
    },
    {
      "currency": "CNY 중국",
      "baseRate": "193.87",
      "change": "0.93",
      "changeDirection": "하락",
      "changeRate": "-0.48",
      "cashBuy": "205.50",
      "cashSell": "184.18",
      "send": "195.80",
      "receive": "191.94"
    },
    {
      "currency": "HKD 홍콩",
      "baseRate": "177.65",
      "change": "1.27",
      "changeDirection": "하락",
      "changeRate": "-0.71",
      "cashBuy": "181.18",
      "cashSell": "174.12",
      "send": "179.42",
      "receive": "175.88"
    },
    {
      "currency": "GBP 영국",
      "baseRate": "1,872.43",
      "change": "3.26",
      "changeDirection": "하락",
      "changeRate": "-0.17",
      "cashBuy": "1,909.69",
      "cashSell": "1,835.17",
      "send": "1,891.15",
      "receive": "1,853.71"
    },
    {
      "currency": "CHF 스위스",
      "baseRate": "1,729.83",
      "change": "1.33",
      "changeDirection": "상승",
      "changeRate": "0.08",
      "cashBuy": "1,764.25",
      "cashSell": "1,695.41",
      "send": "1,747.12",
      "receive": "1,712.54"
    },
    {
      "currency": "CAD 캐나다",
      "baseRate": "1,003.33",
      "change": "2.06",
      "changeDirection": "하락",
      "changeRate": "-0.20",
      "cashBuy": "1,023.29",
      "cashSell": "983.37",
      "send": "1,013.36",
      "receive": "993.30"
    },
    {
      "currency": "AUD 호주",
      "baseRate": "900.63",
      "change": "2.70",
      "changeDirection": "상승",
      "changeRate": "0.30",
      "cashBuy": "918.55",
      "cashSell": "882.71",
      "send": "909.63",
      "receive": "891.63"
    },
    {
      "currency": "NZD 뉴질랜드",
      "baseRate": "813.35",
      "change": "0.41",
      "changeDirection": "하락",
      "changeRate": "-0.05",
      "cashBuy": "829.53",
      "cashSell": "797.17",
      "send": "821.48",
      "receive": "805.22"
    },
    {
      "currency": "SEK 스웨덴",
      "baseRate": "145.63",
      "change": "0.32",
      "changeDirection": "상승",
      "changeRate": "0.22",
      "cashBuy": "149.27",
      "cashSell": "141.99",
      "send": "147.08",
      "receive": "144.18"
    },
    {
      "currency": "DKK 덴마크",
      "baseRate": "217.43",
      "change": "0.04",
      "changeDirection": "하락",
      "changeRate": "-0.02",
      "cashBuy": "222.86",
      "cashSell": "212.00",
      "send": "219.60",
      "receive": "215.26"
    },
    {
      "currency": "NOK 노르웨이",
      "baseRate": "137.27",
      "change": "0.05",
      "changeDirection": "하락",
      "changeRate": "-0.04",
      "cashBuy": "140.70",
      "cashSell": "133.84",
      "send": "138.64",
      "receive": "135.90"
    },
    {
      "currency": "SAR 사우디아라비아",
      "baseRate": "369.78",
      "change": "2.77",
      "changeDirection": "하락",
      "changeRate": "-0.74",
      "cashBuy": "388.26",
      "cashSell": "343.90",
      "send": "373.47",
      "receive": "366.09"
    },
    {
      "currency": "KWD 쿠웨이트",
      "baseRate": "4,542.78",
      "change": "27.67",
      "changeDirection": "하락",
      "changeRate": "-0.61",
      "cashBuy": "4,815.34",
      "cashSell": "4,179.36",
      "send": "4,588.20",
      "receive": "4,497.36"
    },
    {
      "currency": "BHD 바레인",
      "baseRate": "3,679.98",
      "change": "28.11",
      "changeDirection": "하락",
      "changeRate": "-0.76",
      "cashBuy": "3,900.77",
      "cashSell": "3,385.59",
      "send": "3,716.77",
      "receive": "3,643.19"
    },
    {
      "currency": "AED 아랍에미리트",
      "baseRate": "377.78",
      "change": "2.88",
      "changeDirection": "하락",
      "changeRate": "-0.76",
      "cashBuy": "396.66",
      "cashSell": "351.34",
      "send": "381.55",
      "receive": "374.01"
    },
    {
      "currency": "THB 태국",
      "baseRate": "42.77",
      "change": "0.02",
      "changeDirection": "하락",
      "changeRate": "-0.05",
      "cashBuy": "45.31",
      "cashSell": "39.78",
      "send": "43.19",
      "receive": "42.35"
    },
    {
      "currency": "SGD 싱가포르",
      "baseRate": "1,081.37",
      "change": "3.40",
      "changeDirection": "하락",
      "changeRate": "-0.31",
      "cashBuy": "1,102.99",
      "cashSell": "1,059.75",
      "send": "1,092.18",
      "receive": "1,070.56"
    },
    {
      "currency": "IDR 인도네시아",
      "baseRate": "8.54",
      "change": "0.05",
      "changeDirection": "하락",
      "changeRate": "-0.58",
      "cashBuy": "9.22",
      "cashSell": "7.61",
      "send": "8.62",
      "receive": "8.46"
    },
    {
      "currency": "INR 인도",
      "baseRate": "15.89",
      "change": "0.13",
      "changeDirection": "하락",
      "changeRate": "-0.81",
      "cashBuy": "17.32",
      "cashSell": "14.46",
      "send": "16.04",
      "receive": "15.74"
    },
    {
      "currency": "MYR 말레이시아",
      "baseRate": "329.77",
      "change": "1.18",
      "changeDirection": "하락",
      "changeRate": "-0.36",
      "cashBuy": "349.55",
      "cashSell": "303.39",
      "send": "333.06",
      "receive": "326.48"
    },
    {
      "currency": "PKR 파키스탄",
      "baseRate": "4.89",
      "change": "0.04",
      "changeDirection": "하락",
      "changeRate": "-0.81",
      "cashBuy": "5.28",
      "cashSell": "4.50",
      "send": "4.93",
      "receive": "4.85"
    },
    {
      "currency": "BDT 방글라데시",
      "baseRate": "11.40",
      "change": "0.10",
      "changeDirection": "하락",
      "changeRate": "-0.87",
      "cashBuy": "12.31",
      "cashSell": "10.49",
      "send": "11.51",
      "receive": "11.29"
    },
    {
      "currency": "PHP 필리핀",
      "baseRate": "24.46",
      "change": "0.01",
      "changeDirection": "상승",
      "changeRate": "0.04",
      "cashBuy": "26.90",
      "cashSell": "22.75",
      "send": "24.70",
      "receive": "24.22"
    },
    {
      "currency": "EGP 이집트",
      "baseRate": "28.66",
      "change": "0.17",
      "changeDirection": "하락",
      "changeRate": "-0.59",
      "cashBuy": "30.95",
      "cashSell": "26.66",
      "send": "28.94",
      "receive": "28.38"
    },
    {
      "currency": "MXN 멕시코",
      "baseRate": "74.62",
      "change": "0.05",
      "changeDirection": "상승",
      "changeRate": "0.07",
      "cashBuy": "80.58",
      "cashSell": "68.66",
      "send": "75.36",
      "receive": "73.88"
    },
    {
      "currency": "BND 브루나이",
      "baseRate": "1,082.21",
      "change": "2.56",
      "changeDirection": "하락",
      "changeRate": "-0.24",
      "cashBuy": "1,125.49",
      "cashSell": "1,017.28",
      "send": "1,093.03",
      "receive": "1,071.39"
    }
  ],
  "date": "2025년08월25일",
  "round": "511"
}